ornamentation/__init__.py
ornamentation/debug.py
ornamentation/django.py
ornamentation/misc.py
ornamentation-0.5.0.dist-info/LICENSE
ornamentation-0.5.0.dist-info/METADATA
ornamentation-0.5.0.dist-info/WHEEL
ornamentation-0.5.0.dist-info/top_level.txt
ornamentation-0.5.0.dist-info/RECORD
